{
  "id": "20260621-github-huggingfacetransform",
  "title": "huggingface/transformers",
  "source_url": "https://github.com/huggingface/transformers",
  "source_type": "github_trending",
  "summary": "Hugging Face Transformers 是一个提供数千种预训练模型（如BERT、GPT、T5）的库，支持PyTorch、TensorFlow和JAX，用于自然语言处理、计算机视觉等任务。",
  "highlights": [
    "支持超过50种架构和数千个预训练模型",
    "统一的API，轻松切换不同框架",
    "活跃的社区和丰富的文档与教程"
  ],
  "use_cases": [
    "文本分类、情感分析、问答系统",
    "图像分类、目标检测、文本生成"
  ],
  "maturity": {
    "stars": 130000,
    "last_updated": "2026-06-01",
    "production_ready": true
  },
  "tags": [
    "nlp",
    "deep-learning",
    "pretrained-models",
    "pytorch",
    "tensorflow"
  ],
  "status": "curated",
  "collected_at": "2026-06-21T15:38:07Z",
  "analyzed_at": "2026-06-21T15:38:28Z",
  "curated_at": "2026-06-21T15:39:12Z"
}